Metadata-Version: 2.4
Name: image-processing-package-master
Version: 0.0.1
Summary: Image Processing Package using skimage
Home-page: https://github.com/Pedro-H-Goulart/image_processing_DIO
Author: Pedro
Requires-Python: >=3.5
Requires-Dist: matplotlib
Requires-Dist: numpy
Requires-Dist: scikit-image>=0.16.1
Dynamic: author
Dynamic: description
Dynamic: description-content-type
Dynamic: home-page
Dynamic: requires-dist
Dynamic: requires-python
Dynamic: summary
